RsCmwBluetoothMeas/RsCmwBluetoothMeas.py
RsCmwBluetoothMeas/__init__.py
RsCmwBluetoothMeas/enums.py
RsCmwBluetoothMeas/repcap.py
RsCmwBluetoothMeas/CustomFiles/__init__.py
RsCmwBluetoothMeas/CustomFiles/events.py
RsCmwBluetoothMeas/CustomFiles/reliability.py
RsCmwBluetoothMeas/CustomFiles/utilities.py
RsCmwBluetoothMeas/Implementations/__init__.py
RsCmwBluetoothMeas/Implementations/Call/__init__.py
RsCmwBluetoothMeas/Implementations/Call/Csounding/__init__.py
RsCmwBluetoothMeas/Implementations/Call/Csounding/DtMode/Rdevices.py
RsCmwBluetoothMeas/Implementations/Call/Csounding/DtMode/__init__.py
RsCmwBluetoothMeas/Implementations/Call/DtMode/__init__.py
RsCmwBluetoothMeas/Implementations/Call/DtMode/LowEnergy/Rdevices.py
RsCmwBluetoothMeas/Implementations/Call/DtMode/LowEnergy/__init__.py
RsCmwBluetoothMeas/Implementations/Clean/Elogging.py
RsCmwBluetoothMeas/Implementations/Clean/__init__.py
RsCmwBluetoothMeas/Implementations/Configure/Display.py
RsCmwBluetoothMeas/Implementations/Configure/__init__.py
RsCmwBluetoothMeas/Implementations/Configure/ComSettings/Ports.py
RsCmwBluetoothMeas/Implementations/Configure/ComSettings/__init__.py
RsCmwBluetoothMeas/Implementations/Configure/Csounding/Scount.py
RsCmwBluetoothMeas/Implementations/Configure/Csounding/__init__.py
RsCmwBluetoothMeas/Implementations/Configure/Csounding/ComSettings/Ports.py
RsCmwBluetoothMeas/Implementations/Configure/Csounding/ComSettings/__init__.py
RsCmwBluetoothMeas/Implementations/Configure/Csounding/InputSignal/Mmode.py
RsCmwBluetoothMeas/Implementations/Configure/Csounding/InputSignal/Plength.py
RsCmwBluetoothMeas/Implementations/Configure/Csounding/InputSignal/__init__.py
RsCmwBluetoothMeas/Implementations/Configure/Csounding/Limit/Mspectrum.py
RsCmwBluetoothMeas/Implementations/Configure/Csounding/Limit/__init__.py
RsCmwBluetoothMeas/Implementations/Configure/Csounding/Result/All.py
RsCmwBluetoothMeas/Implementations/Configure/Csounding/Result/__init__.py
RsCmwBluetoothMeas-4.0.230.dist-info/METADATA
RsCmwBluetoothMeas-4.0.230.dist-info/WHEEL
RsCmwBluetoothMeas-4.0.230.dist-info/top_level.txt
RsCmwBluetoothMeas-4.0.230.dist-info/RECORD
